assets/favicon.ico
pyshala/.gitignore
pyshala/__init__.py
pyshala/app.py
pyshala/cli.py
pyshala/pyshala.py
pyshala/components/__init__.py
pyshala/components/code_editor.py
pyshala/components/lesson_content.py
pyshala/components/navbar.py
pyshala/components/progress_badge.py
pyshala/components/quiz_form.py
pyshala/components/quiz_toolbar.py
pyshala/components/sidebar.py
pyshala/components/test_results.py
pyshala/models/__init__.py
pyshala/models/config.py
pyshala/models/lesson.py
pyshala/models/module.py
pyshala/models/progress.py
pyshala/pages/__init__.py
pyshala/pages/index.py
pyshala/pages/lesson.py
pyshala/services/__init__.py
pyshala/services/config_loader.py
pyshala/services/judge0_client.py
pyshala/services/lesson_loader.py
pyshala/services/local_executor.py
pyshala/services/progress_db.py
pyshala/state/__init__.py
pyshala/state/app_state.py
pyshala-0.1.1.dist-info/METADATA
pyshala-0.1.1.dist-info/WHEEL
pyshala-0.1.1.dist-info/entry_points.txt
pyshala-0.1.1.dist-info/licenses/LICENSE
pyshala-0.1.1.dist-info/RECORD
