Metadata-Version: 2.4
Name: pyshala
Version: 0.1.1
Summary: A self-hosted interactive Python training platform
Project-URL: Homepage, https://github.com/dkedar7/pyshala
Project-URL: Repository, https://github.com/dkedar7/pyshala
Project-URL: Issues, https://github.com/dkedar7/pyshala/issues
Author-email: Kedar Dabhadkar <kdabhadk@gmail.com>
License: MIT
License-File: LICENSE
Keywords: coding,education,interactive,learning,python,reflex,training
Classifier: Development Status :: 3 - Alpha
Classifier: Intended Audience :: Developers
Classifier: Intended Audience :: Education
Classifier: License :: OSI Approved :: MIT License
Classifier: Programming Language :: Python :: 3
Classifier: Programming Language :: Python :: 3.10
Classifier: Programming Language :: Python :: 3.11
Classifier: Programming Language :: Python :: 3.12
Classifier: Programming Language :: Python :: 3.13
Classifier: Topic :: Education
Classifier: Topic :: Software Development :: Testing
Requires-Python: >=3.10
Requires-Dist: aiosqlite>=0.20.0
Requires-Dist: httpx>=0.27.0
Requires-Dist: markdown>=3.7
Requires-Dist: pyyaml>=6.0
Requires-Dist: reflex-monaco>=0.0.3
Requires-Dist: reflex>=0.6.0
Provides-Extra: dev
Requires-Dist: pytest-asyncio>=0.24.0; extra == 'dev'
Requires-Dist: pytest-cov>=4.0.0; extra == 'dev'
Requires-Dist: pytest>=8.0.0; extra == 'dev'
